SystemSlash/SystemSlash.py
system_slash-0.0.4.dist-info/LICENSE
system_slash-0.0.4.dist-info/METADATA
system_slash-0.0.4.dist-info/WHEEL
system_slash-0.0.4.dist-info/top_level.txt
system_slash-0.0.4.dist-info/RECORD
